[
  {
    "_id": "eng_2_hard_1",
    "content": "Identify the subordinate clause: 'Although it was raining, we went to the park.'",
    "type": "multiple_choice",
    "subject": "English",
    "topic": "Grammar and Language",
    "difficulty": "hard",
    "grade": "2",
    "options": [
      "Although it was raining",
      "it was raining",
      "we went to the park",
      "to the park"
    ],
    "correctAnswer": "Although it was raining",
    "explanation": "A subordinate clause begins with a subordinating conjunction like 'although' and cannot stand alone.",
    "hints": [
      "Think about advanced English grammar rules."
    ],
    "timeLimit": 60,
    "tags": [
      "english",
      "grammar",
      "language"
    ],
    "createdBy": "system",
    "createdAt": "2025-08-11T13:03:46.653Z",
    "isGenerated": true,
    "generatedAt": "2025-08-11T13:03:46.653Z",
    "generationMethod": "english-template-system"
  },
  {
    "_id": "eng_2_hard_2",
    "content": "What literary device is used in 'The wind whispered through the trees'?",
    "type": "multiple_choice",
    "subject": "English",
    "topic": "Grammar and Language",
    "difficulty": "hard",
    "grade": "2",
    "options": [
      "Metaphor",
      "Simile",
      "Personification",
      "Alliteration"
    ],
    "correctAnswer": "Personification",
    "explanation": "Personification gives human qualities (whispering) to non-human things (wind).",
    "hints": [
      "Think about advanced English grammar rules."
    ],
    "timeLimit": 60,
    "tags": [
      "english",
      "grammar",
      "language"
    ],
    "createdBy": "system",
    "createdAt": "2025-08-11T13:03:46.653Z",
    "isGenerated": true,
    "generatedAt": "2025-08-11T13:03:46.653Z",
    "generationMethod": "english-template-system"
  },
  {
    "_id": "eng_2_hard_3",
    "content": "Which sentence uses the subjunctive mood correctly?",
    "type": "multiple_choice",
    "subject": "English",
    "topic": "Grammar and Language",
    "difficulty": "hard",
    "grade": "2",
    "options": [
      "If I was rich, I would travel.",
      "If I were rich, I would travel.",
      "If I am rich, I will travel.",
      "If I will be rich, I would travel."
    ],
    "correctAnswer": "If I were rich, I would travel.",
    "explanation": "The subjunctive mood uses 'were' instead of 'was' in hypothetical situations.",
    "hints": [
      "Think about advanced English grammar rules."
    ],
    "timeLimit": 60,
    "tags": [
      "english",
      "grammar",
      "language"
    ],
    "createdBy": "system",
    "createdAt": "2025-08-11T13:03:46.653Z",
    "isGenerated": true,
    "generatedAt": "2025-08-11T13:03:46.653Z",
    "generationMethod": "english-template-system"
  },
  {
    "_id": "eng_2_hard_4",
    "content": "Identify the subordinate clause: 'Although it was raining, we went to the park.'",
    "type": "multiple_choice",
    "subject": "English",
    "topic": "Grammar and Language",
    "difficulty": "hard",
    "grade": "2",
    "options": [
      "Although it was raining",
      "it was raining",
      "we went to the park",
      "to the park"
    ],
    "correctAnswer": "Although it was raining",
    "explanation": "A subordinate clause begins with a subordinating conjunction like 'although' and cannot stand alone.",
    "hints": [
      "Think about advanced English grammar rules."
    ],
    "timeLimit": 60,
    "tags": [
      "english",
      "grammar",
      "language"
    ],
    "createdBy": "system",
    "createdAt": "2025-08-11T13:03:46.653Z",
    "isGenerated": true,
    "generatedAt": "2025-08-11T13:03:46.653Z",
    "generationMethod": "english-template-system"
  },
  {
    "_id": "eng_2_hard_5",
    "content": "What literary device is used in 'The wind whispered through the trees'?",
    "type": "multiple_choice",
    "subject": "English",
    "topic": "Grammar and Language",
    "difficulty": "hard",
    "grade": "2",
    "options": [
      "Metaphor",
      "Simile",
      "Personification",
      "Alliteration"
    ],
    "correctAnswer": "Personification",
    "explanation": "Personification gives human qualities (whispering) to non-human things (wind).",
    "hints": [
      "Think about advanced English grammar rules."
    ],
    "timeLimit": 60,
    "tags": [
      "english",
      "grammar",
      "language"
    ],
    "createdBy": "system",
    "createdAt": "2025-08-11T13:03:46.653Z",
    "isGenerated": true,
    "generatedAt": "2025-08-11T13:03:46.653Z",
    "generationMethod": "english-template-system"
  },
  {
    "_id": "eng_2_hard_6",
    "content": "Which sentence uses the subjunctive mood correctly?",
    "type": "multiple_choice",
    "subject": "English",
    "topic": "Grammar and Language",
    "difficulty": "hard",
    "grade": "2",
    "options": [
      "If I was rich, I would travel.",
      "If I were rich, I would travel.",
      "If I am rich, I will travel.",
      "If I will be rich, I would travel."
    ],
    "correctAnswer": "If I were rich, I would travel.",
    "explanation": "The subjunctive mood uses 'were' instead of 'was' in hypothetical situations.",
    "hints": [
      "Think about advanced English grammar rules."
    ],
    "timeLimit": 60,
    "tags": [
      "english",
      "grammar",
      "language"
    ],
    "createdBy": "system",
    "createdAt": "2025-08-11T13:03:46.653Z",
    "isGenerated": true,
    "generatedAt": "2025-08-11T13:03:46.653Z",
    "generationMethod": "english-template-system"
  },
  {
    "_id": "eng_2_hard_7",
    "content": "Identify the subordinate clause: 'Although it was raining, we went to the park.'",
    "type": "multiple_choice",
    "subject": "English",
    "topic": "Grammar and Language",
    "difficulty": "hard",
    "grade": "2",
    "options": [
      "Although it was raining",
      "it was raining",
      "we went to the park",
      "to the park"
    ],
    "correctAnswer": "Although it was raining",
    "explanation": "A subordinate clause begins with a subordinating conjunction like 'although' and cannot stand alone.",
    "hints": [
      "Think about advanced English grammar rules."
    ],
    "timeLimit": 60,
    "tags": [
      "english",
      "grammar",
      "language"
    ],
    "createdBy": "system",
    "createdAt": "2025-08-11T13:03:46.653Z",
    "isGenerated": true,
    "generatedAt": "2025-08-11T13:03:46.653Z",
    "generationMethod": "english-template-system"
  },
  {
    "_id": "eng_2_hard_8",
    "content": "What literary device is used in 'The wind whispered through the trees'?",
    "type": "multiple_choice",
    "subject": "English",
    "topic": "Grammar and Language",
    "difficulty": "hard",
    "grade": "2",
    "options": [
      "Metaphor",
      "Simile",
      "Personification",
      "Alliteration"
    ],
    "correctAnswer": "Personification",
    "explanation": "Personification gives human qualities (whispering) to non-human things (wind).",
    "hints": [
      "Think about advanced English grammar rules."
    ],
    "timeLimit": 60,
    "tags": [
      "english",
      "grammar",
      "language"
    ],
    "createdBy": "system",
    "createdAt": "2025-08-11T13:03:46.653Z",
    "isGenerated": true,
    "generatedAt": "2025-08-11T13:03:46.653Z",
    "generationMethod": "english-template-system"
  },
  {
    "_id": "eng_2_hard_9",
    "content": "Which sentence uses the subjunctive mood correctly?",
    "type": "multiple_choice",
    "subject": "English",
    "topic": "Grammar and Language",
    "difficulty": "hard",
    "grade": "2",
    "options": [
      "If I was rich, I would travel.",
      "If I were rich, I would travel.",
      "If I am rich, I will travel.",
      "If I will be rich, I would travel."
    ],
    "correctAnswer": "If I were rich, I would travel.",
    "explanation": "The subjunctive mood uses 'were' instead of 'was' in hypothetical situations.",
    "hints": [
      "Think about advanced English grammar rules."
    ],
    "timeLimit": 60,
    "tags": [
      "english",
      "grammar",
      "language"
    ],
    "createdBy": "system",
    "createdAt": "2025-08-11T13:03:46.653Z",
    "isGenerated": true,
    "generatedAt": "2025-08-11T13:03:46.653Z",
    "generationMethod": "english-template-system"
  },
  {
    "_id": "eng_2_hard_10",
    "content": "Identify the subordinate clause: 'Although it was raining, we went to the park.'",
    "type": "multiple_choice",
    "subject": "English",
    "topic": "Grammar and Language",
    "difficulty": "hard",
    "grade": "2",
    "options": [
      "Although it was raining",
      "it was raining",
      "we went to the park",
      "to the park"
    ],
    "correctAnswer": "Although it was raining",
    "explanation": "A subordinate clause begins with a subordinating conjunction like 'although' and cannot stand alone.",
    "hints": [
      "Think about advanced English grammar rules."
    ],
    "timeLimit": 60,
    "tags": [
      "english",
      "grammar",
      "language"
    ],
    "createdBy": "system",
    "createdAt": "2025-08-11T13:03:46.653Z",
    "isGenerated": true,
    "generatedAt": "2025-08-11T13:03:46.653Z",
    "generationMethod": "english-template-system"
  },
  {
    "_id": "eng_2_hard_11",
    "content": "What literary device is used in 'The wind whispered through the trees'?",
    "type": "multiple_choice",
    "subject": "English",
    "topic": "Grammar and Language",
    "difficulty": "hard",
    "grade": "2",
    "options": [
      "Metaphor",
      "Simile",
      "Personification",
      "Alliteration"
    ],
    "correctAnswer": "Personification",
    "explanation": "Personification gives human qualities (whispering) to non-human things (wind).",
    "hints": [
      "Think about advanced English grammar rules."
    ],
    "timeLimit": 60,
    "tags": [
      "english",
      "grammar",
      "language"
    ],
    "createdBy": "system",
    "createdAt": "2025-08-11T13:03:46.653Z",
    "isGenerated": true,
    "generatedAt": "2025-08-11T13:03:46.653Z",
    "generationMethod": "english-template-system"
  },
  {
    "_id": "eng_2_hard_12",
    "content": "Which sentence uses the subjunctive mood correctly?",
    "type": "multiple_choice",
    "subject": "English",
    "topic": "Grammar and Language",
    "difficulty": "hard",
    "grade": "2",
    "options": [
      "If I was rich, I would travel.",
      "If I were rich, I would travel.",
      "If I am rich, I will travel.",
      "If I will be rich, I would travel."
    ],
    "correctAnswer": "If I were rich, I would travel.",
    "explanation": "The subjunctive mood uses 'were' instead of 'was' in hypothetical situations.",
    "hints": [
      "Think about advanced English grammar rules."
    ],
    "timeLimit": 60,
    "tags": [
      "english",
      "grammar",
      "language"
    ],
    "createdBy": "system",
    "createdAt": "2025-08-11T13:03:46.653Z",
    "isGenerated": true,
    "generatedAt": "2025-08-11T13:03:46.653Z",
    "generationMethod": "english-template-system"
  },
  {
    "_id": "eng_2_hard_13",
    "content": "Identify the subordinate clause: 'Although it was raining, we went to the park.'",
    "type": "multiple_choice",
    "subject": "English",
    "topic": "Grammar and Language",
    "difficulty": "hard",
    "grade": "2",
    "options": [
      "Although it was raining",
      "it was raining",
      "we went to the park",
      "to the park"
    ],
    "correctAnswer": "Although it was raining",
    "explanation": "A subordinate clause begins with a subordinating conjunction like 'although' and cannot stand alone.",
    "hints": [
      "Think about advanced English grammar rules."
    ],
    "timeLimit": 60,
    "tags": [
      "english",
      "grammar",
      "language"
    ],
    "createdBy": "system",
    "createdAt": "2025-08-11T13:03:46.653Z",
    "isGenerated": true,
    "generatedAt": "2025-08-11T13:03:46.653Z",
    "generationMethod": "english-template-system"
  },
  {
    "_id": "eng_2_hard_14",
    "content": "What literary device is used in 'The wind whispered through the trees'?",
    "type": "multiple_choice",
    "subject": "English",
    "topic": "Grammar and Language",
    "difficulty": "hard",
    "grade": "2",
    "options": [
      "Metaphor",
      "Simile",
      "Personification",
      "Alliteration"
    ],
    "correctAnswer": "Personification",
    "explanation": "Personification gives human qualities (whispering) to non-human things (wind).",
    "hints": [
      "Think about advanced English grammar rules."
    ],
    "timeLimit": 60,
    "tags": [
      "english",
      "grammar",
      "language"
    ],
    "createdBy": "system",
    "createdAt": "2025-08-11T13:03:46.653Z",
    "isGenerated": true,
    "generatedAt": "2025-08-11T13:03:46.653Z",
    "generationMethod": "english-template-system"
  },
  {
    "_id": "eng_2_hard_15",
    "content": "Which sentence uses the subjunctive mood correctly?",
    "type": "multiple_choice",
    "subject": "English",
    "topic": "Grammar and Language",
    "difficulty": "hard",
    "grade": "2",
    "options": [
      "If I was rich, I would travel.",
      "If I were rich, I would travel.",
      "If I am rich, I will travel.",
      "If I will be rich, I would travel."
    ],
    "correctAnswer": "If I were rich, I would travel.",
    "explanation": "The subjunctive mood uses 'were' instead of 'was' in hypothetical situations.",
    "hints": [
      "Think about advanced English grammar rules."
    ],
    "timeLimit": 60,
    "tags": [
      "english",
      "grammar",
      "language"
    ],
    "createdBy": "system",
    "createdAt": "2025-08-11T13:03:46.653Z",
    "isGenerated": true,
    "generatedAt": "2025-08-11T13:03:46.653Z",
    "generationMethod": "english-template-system"
  },
  {
    "_id": "eng_2_hard_16",
    "content": "Identify the subordinate clause: 'Although it was raining, we went to the park.'",
    "type": "multiple_choice",
    "subject": "English",
    "topic": "Grammar and Language",
    "difficulty": "hard",
    "grade": "2",
    "options": [
      "Although it was raining",
      "it was raining",
      "we went to the park",
      "to the park"
    ],
    "correctAnswer": "Although it was raining",
    "explanation": "A subordinate clause begins with a subordinating conjunction like 'although' and cannot stand alone.",
    "hints": [
      "Think about advanced English grammar rules."
    ],
    "timeLimit": 60,
    "tags": [
      "english",
      "grammar",
      "language"
    ],
    "createdBy": "system",
    "createdAt": "2025-08-11T13:03:46.653Z",
    "isGenerated": true,
    "generatedAt": "2025-08-11T13:03:46.653Z",
    "generationMethod": "english-template-system"
  },
  {
    "_id": "eng_2_hard_17",
    "content": "What literary device is used in 'The wind whispered through the trees'?",
    "type": "multiple_choice",
    "subject": "English",
    "topic": "Grammar and Language",
    "difficulty": "hard",
    "grade": "2",
    "options": [
      "Metaphor",
      "Simile",
      "Personification",
      "Alliteration"
    ],
    "correctAnswer": "Personification",
    "explanation": "Personification gives human qualities (whispering) to non-human things (wind).",
    "hints": [
      "Think about advanced English grammar rules."
    ],
    "timeLimit": 60,
    "tags": [
      "english",
      "grammar",
      "language"
    ],
    "createdBy": "system",
    "createdAt": "2025-08-11T13:03:46.653Z",
    "isGenerated": true,
    "generatedAt": "2025-08-11T13:03:46.653Z",
    "generationMethod": "english-template-system"
  },
  {
    "_id": "eng_2_hard_18",
    "content": "Which sentence uses the subjunctive mood correctly?",
    "type": "multiple_choice",
    "subject": "English",
    "topic": "Grammar and Language",
    "difficulty": "hard",
    "grade": "2",
    "options": [
      "If I was rich, I would travel.",
      "If I were rich, I would travel.",
      "If I am rich, I will travel.",
      "If I will be rich, I would travel."
    ],
    "correctAnswer": "If I were rich, I would travel.",
    "explanation": "The subjunctive mood uses 'were' instead of 'was' in hypothetical situations.",
    "hints": [
      "Think about advanced English grammar rules."
    ],
    "timeLimit": 60,
    "tags": [
      "english",
      "grammar",
      "language"
    ],
    "createdBy": "system",
    "createdAt": "2025-08-11T13:03:46.653Z",
    "isGenerated": true,
    "generatedAt": "2025-08-11T13:03:46.653Z",
    "generationMethod": "english-template-system"
  },
  {
    "_id": "eng_2_hard_19",
    "content": "Identify the subordinate clause: 'Although it was raining, we went to the park.'",
    "type": "multiple_choice",
    "subject": "English",
    "topic": "Grammar and Language",
    "difficulty": "hard",
    "grade": "2",
    "options": [
      "Although it was raining",
      "it was raining",
      "we went to the park",
      "to the park"
    ],
    "correctAnswer": "Although it was raining",
    "explanation": "A subordinate clause begins with a subordinating conjunction like 'although' and cannot stand alone.",
    "hints": [
      "Think about advanced English grammar rules."
    ],
    "timeLimit": 60,
    "tags": [
      "english",
      "grammar",
      "language"
    ],
    "createdBy": "system",
    "createdAt": "2025-08-11T13:03:46.653Z",
    "isGenerated": true,
    "generatedAt": "2025-08-11T13:03:46.653Z",
    "generationMethod": "english-template-system"
  },
  {
    "_id": "eng_2_hard_20",
    "content": "What literary device is used in 'The wind whispered through the trees'?",
    "type": "multiple_choice",
    "subject": "English",
    "topic": "Grammar and Language",
    "difficulty": "hard",
    "grade": "2",
    "options": [
      "Metaphor",
      "Simile",
      "Personification",
      "Alliteration"
    ],
    "correctAnswer": "Personification",
    "explanation": "Personification gives human qualities (whispering) to non-human things (wind).",
    "hints": [
      "Think about advanced English grammar rules."
    ],
    "timeLimit": 60,
    "tags": [
      "english",
      "grammar",
      "language"
    ],
    "createdBy": "system",
    "createdAt": "2025-08-11T13:03:46.653Z",
    "isGenerated": true,
    "generatedAt": "2025-08-11T13:03:46.653Z",
    "generationMethod": "english-template-system"
  },
  {
    "_id": "eng_2_hard_21",
    "content": "Which sentence uses the subjunctive mood correctly?",
    "type": "multiple_choice",
    "subject": "English",
    "topic": "Grammar and Language",
    "difficulty": "hard",
    "grade": "2",
    "options": [
      "If I was rich, I would travel.",
      "If I were rich, I would travel.",
      "If I am rich, I will travel.",
      "If I will be rich, I would travel."
    ],
    "correctAnswer": "If I were rich, I would travel.",
    "explanation": "The subjunctive mood uses 'were' instead of 'was' in hypothetical situations.",
    "hints": [
      "Think about advanced English grammar rules."
    ],
    "timeLimit": 60,
    "tags": [
      "english",
      "grammar",
      "language"
    ],
    "createdBy": "system",
    "createdAt": "2025-08-11T13:03:46.653Z",
    "isGenerated": true,
    "generatedAt": "2025-08-11T13:03:46.653Z",
    "generationMethod": "english-template-system"
  },
  {
    "_id": "eng_2_hard_22",
    "content": "Identify the subordinate clause: 'Although it was raining, we went to the park.'",
    "type": "multiple_choice",
    "subject": "English",
    "topic": "Grammar and Language",
    "difficulty": "hard",
    "grade": "2",
    "options": [
      "Although it was raining",
      "it was raining",
      "we went to the park",
      "to the park"
    ],
    "correctAnswer": "Although it was raining",
    "explanation": "A subordinate clause begins with a subordinating conjunction like 'although' and cannot stand alone.",
    "hints": [
      "Think about advanced English grammar rules."
    ],
    "timeLimit": 60,
    "tags": [
      "english",
      "grammar",
      "language"
    ],
    "createdBy": "system",
    "createdAt": "2025-08-11T13:03:46.653Z",
    "isGenerated": true,
    "generatedAt": "2025-08-11T13:03:46.653Z",
    "generationMethod": "english-template-system"
  },
  {
    "_id": "eng_2_hard_23",
    "content": "What literary device is used in 'The wind whispered through the trees'?",
    "type": "multiple_choice",
    "subject": "English",
    "topic": "Grammar and Language",
    "difficulty": "hard",
    "grade": "2",
    "options": [
      "Metaphor",
      "Simile",
      "Personification",
      "Alliteration"
    ],
    "correctAnswer": "Personification",
    "explanation": "Personification gives human qualities (whispering) to non-human things (wind).",
    "hints": [
      "Think about advanced English grammar rules."
    ],
    "timeLimit": 60,
    "tags": [
      "english",
      "grammar",
      "language"
    ],
    "createdBy": "system",
    "createdAt": "2025-08-11T13:03:46.653Z",
    "isGenerated": true,
    "generatedAt": "2025-08-11T13:03:46.653Z",
    "generationMethod": "english-template-system"
  },
  {
    "_id": "eng_2_hard_24",
    "content": "Which sentence uses the subjunctive mood correctly?",
    "type": "multiple_choice",
    "subject": "English",
    "topic": "Grammar and Language",
    "difficulty": "hard",
    "grade": "2",
    "options": [
      "If I was rich, I would travel.",
      "If I were rich, I would travel.",
      "If I am rich, I will travel.",
      "If I will be rich, I would travel."
    ],
    "correctAnswer": "If I were rich, I would travel.",
    "explanation": "The subjunctive mood uses 'were' instead of 'was' in hypothetical situations.",
    "hints": [
      "Think about advanced English grammar rules."
    ],
    "timeLimit": 60,
    "tags": [
      "english",
      "grammar",
      "language"
    ],
    "createdBy": "system",
    "createdAt": "2025-08-11T13:03:46.653Z",
    "isGenerated": true,
    "generatedAt": "2025-08-11T13:03:46.653Z",
    "generationMethod": "english-template-system"
  },
  {
    "_id": "eng_2_hard_25",
    "content": "Identify the subordinate clause: 'Although it was raining, we went to the park.'",
    "type": "multiple_choice",
    "subject": "English",
    "topic": "Grammar and Language",
    "difficulty": "hard",
    "grade": "2",
    "options": [
      "Although it was raining",
      "it was raining",
      "we went to the park",
      "to the park"
    ],
    "correctAnswer": "Although it was raining",
    "explanation": "A subordinate clause begins with a subordinating conjunction like 'although' and cannot stand alone.",
    "hints": [
      "Think about advanced English grammar rules."
    ],
    "timeLimit": 60,
    "tags": [
      "english",
      "grammar",
      "language"
    ],
    "createdBy": "system",
    "createdAt": "2025-08-11T13:03:46.653Z",
    "isGenerated": true,
    "generatedAt": "2025-08-11T13:03:46.653Z",
    "generationMethod": "english-template-system"
  }
]