[
  {
    "_id": "build_math_4_hard_0",
    "content": "What is 83 + 49?",
    "type": "multiple_choice",
    "options": [
      "131",
      "134",
      "132",
      "133"
    ],
    "correctAnswer": "132",
    "explanation": "83 + 49 = 132",
    "subject": "Mathematical Reasoning",
    "topic": "Addition",
    "difficulty": "hard",
    "grade": 4,
    "tags": [
      "mathematics",
      "build-time-generated",
      "timed-test-ready"
    ],
    "createdBy": "build-time-generator",
    "createdAt": "2025-08-11T14:57:08.416Z",
    "estimatedTime": 90
  },
  {
    "_id": "build_math_4_hard_1",
    "content": "What is 27 - 24?",
    "type": "multiple_choice",
    "options": [
      "4",
      "3",
      "2",
      "5"
    ],
    "correctAnswer": "3",
    "explanation": "27 - 24 = 3",
    "subject": "Mathematical Reasoning",
    "topic": "Subtraction",
    "difficulty": "hard",
    "grade": 4,
    "tags": [
      "mathematics",
      "build-time-generated",
      "timed-test-ready"
    ],
    "createdBy": "build-time-generator",
    "createdAt": "2025-08-11T14:57:08.416Z",
    "estimatedTime": 90
  },
  {
    "_id": "build_math_4_hard_2",
    "content": "What is 10 × 6?",
    "type": "multiple_choice",
    "options": [
      "62",
      "61",
      "60",
      "59"
    ],
    "correctAnswer": "60",
    "explanation": "10 × 6 = 60",
    "subject": "Mathematical Reasoning",
    "topic": "Multiplication",
    "difficulty": "hard",
    "grade": 4,
    "tags": [
      "mathematics",
      "build-time-generated",
      "timed-test-ready"
    ],
    "createdBy": "build-time-generator",
    "createdAt": "2025-08-11T14:57:08.416Z",
    "estimatedTime": 90
  },
  {
    "_id": "build_math_4_hard_3",
    "content": "What is 78 ÷ 6?",
    "type": "multiple_choice",
    "options": [
      "12",
      "13",
      "14",
      "15"
    ],
    "correctAnswer": "13",
    "explanation": "78 ÷ 6 = 13",
    "subject": "Mathematical Reasoning",
    "topic": "Division",
    "difficulty": "hard",
    "grade": 4,
    "tags": [
      "mathematics",
      "build-time-generated",
      "timed-test-ready"
    ],
    "createdBy": "build-time-generator",
    "createdAt": "2025-08-11T14:57:08.416Z",
    "estimatedTime": 90
  },
  {
    "_id": "build_math_4_hard_4",
    "content": "What is 45 + 76?",
    "type": "multiple_choice",
    "options": [
      "123",
      "121",
      "122",
      "120"
    ],
    "correctAnswer": "121",
    "explanation": "45 + 76 = 121",
    "subject": "Mathematical Reasoning",
    "topic": "Addition",
    "difficulty": "hard",
    "grade": 4,
    "tags": [
      "mathematics",
      "build-time-generated",
      "timed-test-ready"
    ],
    "createdBy": "build-time-generator",
    "createdAt": "2025-08-11T14:57:08.416Z",
    "estimatedTime": 90
  },
  {
    "_id": "build_math_4_hard_5",
    "content": "What is 27 - 3?",
    "type": "multiple_choice",
    "options": [
      "25",
      "26",
      "24",
      "23"
    ],
    "correctAnswer": "24",
    "explanation": "27 - 3 = 24",
    "subject": "Mathematical Reasoning",
    "topic": "Subtraction",
    "difficulty": "hard",
    "grade": 4,
    "tags": [
      "mathematics",
      "build-time-generated",
      "timed-test-ready"
    ],
    "createdBy": "build-time-generator",
    "createdAt": "2025-08-11T14:57:08.416Z",
    "estimatedTime": 90
  },
  {
    "_id": "build_math_4_hard_6",
    "content": "What is 2 × 5?",
    "type": "multiple_choice",
    "options": [
      "10",
      "9",
      "11",
      "12"
    ],
    "correctAnswer": "10",
    "explanation": "2 × 5 = 10",
    "subject": "Mathematical Reasoning",
    "topic": "Multiplication",
    "difficulty": "hard",
    "grade": 4,
    "tags": [
      "mathematics",
      "build-time-generated",
      "timed-test-ready"
    ],
    "createdBy": "build-time-generator",
    "createdAt": "2025-08-11T14:57:08.416Z",
    "estimatedTime": 90
  },
  {
    "_id": "build_math_4_hard_7",
    "content": "What is 110 ÷ 10?",
    "type": "multiple_choice",
    "options": [
      "10",
      "12",
      "11",
      "13"
    ],
    "correctAnswer": "11",
    "explanation": "110 ÷ 10 = 11",
    "subject": "Mathematical Reasoning",
    "topic": "Division",
    "difficulty": "hard",
    "grade": 4,
    "tags": [
      "mathematics",
      "build-time-generated",
      "timed-test-ready"
    ],
    "createdBy": "build-time-generator",
    "createdAt": "2025-08-11T14:57:08.416Z",
    "estimatedTime": 90
  },
  {
    "_id": "build_math_4_hard_8",
    "content": "What is 28 + 67?",
    "type": "multiple_choice",
    "options": [
      "97",
      "96",
      "95",
      "94"
    ],
    "correctAnswer": "95",
    "explanation": "28 + 67 = 95",
    "subject": "Mathematical Reasoning",
    "topic": "Addition",
    "difficulty": "hard",
    "grade": 4,
    "tags": [
      "mathematics",
      "build-time-generated",
      "timed-test-ready"
    ],
    "createdBy": "build-time-generator",
    "createdAt": "2025-08-11T14:57:08.416Z",
    "estimatedTime": 90
  },
  {
    "_id": "build_math_4_hard_9",
    "content": "What is 21 - 14?",
    "type": "multiple_choice",
    "options": [
      "6",
      "9",
      "8",
      "7"
    ],
    "correctAnswer": "7",
    "explanation": "21 - 14 = 7",
    "subject": "Mathematical Reasoning",
    "topic": "Subtraction",
    "difficulty": "hard",
    "grade": 4,
    "tags": [
      "mathematics",
      "build-time-generated",
      "timed-test-ready"
    ],
    "createdBy": "build-time-generator",
    "createdAt": "2025-08-11T14:57:08.416Z",
    "estimatedTime": 90
  },
  {
    "_id": "build_math_4_hard_10",
    "content": "What is 4 × 2?",
    "type": "multiple_choice",
    "options": [
      "8",
      "9",
      "7",
      "10"
    ],
    "correctAnswer": "8",
    "explanation": "4 × 2 = 8",
    "subject": "Mathematical Reasoning",
    "topic": "Multiplication",
    "difficulty": "hard",
    "grade": 4,
    "tags": [
      "mathematics",
      "build-time-generated",
      "timed-test-ready"
    ],
    "createdBy": "build-time-generator",
    "createdAt": "2025-08-11T14:57:08.416Z",
    "estimatedTime": 90
  },
  {
    "_id": "build_math_4_hard_11",
    "content": "What is 72 ÷ 9?",
    "type": "multiple_choice",
    "options": [
      "7",
      "9",
      "8",
      "10"
    ],
    "correctAnswer": "8",
    "explanation": "72 ÷ 9 = 8",
    "subject": "Mathematical Reasoning",
    "topic": "Division",
    "difficulty": "hard",
    "grade": 4,
    "tags": [
      "mathematics",
      "build-time-generated",
      "timed-test-ready"
    ],
    "createdBy": "build-time-generator",
    "createdAt": "2025-08-11T14:57:08.416Z",
    "estimatedTime": 90
  },
  {
    "_id": "build_math_4_hard_12",
    "content": "What is 25 + 89?",
    "type": "multiple_choice",
    "options": [
      "114",
      "115",
      "116",
      "113"
    ],
    "correctAnswer": "114",
    "explanation": "25 + 89 = 114",
    "subject": "Mathematical Reasoning",
    "topic": "Addition",
    "difficulty": "hard",
    "grade": 4,
    "tags": [
      "mathematics",
      "build-time-generated",
      "timed-test-ready"
    ],
    "createdBy": "build-time-generator",
    "createdAt": "2025-08-11T14:57:08.416Z",
    "estimatedTime": 90
  },
  {
    "_id": "build_math_4_hard_13",
    "content": "What is 32 - 19?",
    "type": "multiple_choice",
    "options": [
      "13",
      "15",
      "12",
      "14"
    ],
    "correctAnswer": "13",
    "explanation": "32 - 19 = 13",
    "subject": "Mathematical Reasoning",
    "topic": "Subtraction",
    "difficulty": "hard",
    "grade": 4,
    "tags": [
      "mathematics",
      "build-time-generated",
      "timed-test-ready"
    ],
    "createdBy": "build-time-generator",
    "createdAt": "2025-08-11T14:57:08.416Z",
    "estimatedTime": 90
  },
  {
    "_id": "build_math_4_hard_14",
    "content": "What is 3 × 7?",
    "type": "multiple_choice",
    "options": [
      "20",
      "21",
      "23",
      "22"
    ],
    "correctAnswer": "21",
    "explanation": "3 × 7 = 21",
    "subject": "Mathematical Reasoning",
    "topic": "Multiplication",
    "difficulty": "hard",
    "grade": 4,
    "tags": [
      "mathematics",
      "build-time-generated",
      "timed-test-ready"
    ],
    "createdBy": "build-time-generator",
    "createdAt": "2025-08-11T14:57:08.416Z",
    "estimatedTime": 90
  },
  {
    "_id": "build_math_4_hard_15",
    "content": "What is 56 ÷ 7?",
    "type": "multiple_choice",
    "options": [
      "10",
      "9",
      "8",
      "7"
    ],
    "correctAnswer": "8",
    "explanation": "56 ÷ 7 = 8",
    "subject": "Mathematical Reasoning",
    "topic": "Division",
    "difficulty": "hard",
    "grade": 4,
    "tags": [
      "mathematics",
      "build-time-generated",
      "timed-test-ready"
    ],
    "createdBy": "build-time-generator",
    "createdAt": "2025-08-11T14:57:08.416Z",
    "estimatedTime": 90
  },
  {
    "_id": "build_math_4_hard_16",
    "content": "What is 95 + 58?",
    "type": "multiple_choice",
    "options": [
      "155",
      "154",
      "153",
      "152"
    ],
    "correctAnswer": "153",
    "explanation": "95 + 58 = 153",
    "subject": "Mathematical Reasoning",
    "topic": "Addition",
    "difficulty": "hard",
    "grade": 4,
    "tags": [
      "mathematics",
      "build-time-generated",
      "timed-test-ready"
    ],
    "createdBy": "build-time-generator",
    "createdAt": "2025-08-11T14:57:08.416Z",
    "estimatedTime": 90
  },
  {
    "_id": "build_math_4_hard_17",
    "content": "What is 66 - 7?",
    "type": "multiple_choice",
    "options": [
      "61",
      "60",
      "59",
      "58"
    ],
    "correctAnswer": "59",
    "explanation": "66 - 7 = 59",
    "subject": "Mathematical Reasoning",
    "topic": "Subtraction",
    "difficulty": "hard",
    "grade": 4,
    "tags": [
      "mathematics",
      "build-time-generated",
      "timed-test-ready"
    ],
    "createdBy": "build-time-generator",
    "createdAt": "2025-08-11T14:57:08.416Z",
    "estimatedTime": 90
  },
  {
    "_id": "build_math_4_hard_18",
    "content": "What is 4 × 12?",
    "type": "multiple_choice",
    "options": [
      "50",
      "49",
      "48",
      "47"
    ],
    "correctAnswer": "48",
    "explanation": "4 × 12 = 48",
    "subject": "Mathematical Reasoning",
    "topic": "Multiplication",
    "difficulty": "hard",
    "grade": 4,
    "tags": [
      "mathematics",
      "build-time-generated",
      "timed-test-ready"
    ],
    "createdBy": "build-time-generator",
    "createdAt": "2025-08-11T14:57:08.416Z",
    "estimatedTime": 90
  },
  {
    "_id": "build_math_4_hard_19",
    "content": "What is 48 ÷ 8?",
    "type": "multiple_choice",
    "options": [
      "8",
      "6",
      "5",
      "7"
    ],
    "correctAnswer": "6",
    "explanation": "48 ÷ 8 = 6",
    "subject": "Mathematical Reasoning",
    "topic": "Division",
    "difficulty": "hard",
    "grade": 4,
    "tags": [
      "mathematics",
      "build-time-generated",
      "timed-test-ready"
    ],
    "createdBy": "build-time-generator",
    "createdAt": "2025-08-11T14:57:08.416Z",
    "estimatedTime": 90
  },
  {
    "_id": "build_math_4_hard_20",
    "content": "What is 41 + 41?",
    "type": "multiple_choice",
    "options": [
      "83",
      "82",
      "84",
      "81"
    ],
    "correctAnswer": "82",
    "explanation": "41 + 41 = 82",
    "subject": "Mathematical Reasoning",
    "topic": "Addition",
    "difficulty": "hard",
    "grade": 4,
    "tags": [
      "mathematics",
      "build-time-generated",
      "timed-test-ready"
    ],
    "createdBy": "build-time-generator",
    "createdAt": "2025-08-11T14:57:08.416Z",
    "estimatedTime": 90
  },
  {
    "_id": "build_math_4_hard_21",
    "content": "What is 57 - 37?",
    "type": "multiple_choice",
    "options": [
      "19",
      "20",
      "22",
      "21"
    ],
    "correctAnswer": "20",
    "explanation": "57 - 37 = 20",
    "subject": "Mathematical Reasoning",
    "topic": "Subtraction",
    "difficulty": "hard",
    "grade": 4,
    "tags": [
      "mathematics",
      "build-time-generated",
      "timed-test-ready"
    ],
    "createdBy": "build-time-generator",
    "createdAt": "2025-08-11T14:57:08.416Z",
    "estimatedTime": 90
  },
  {
    "_id": "build_math_4_hard_22",
    "content": "What is 7 × 11?",
    "type": "multiple_choice",
    "options": [
      "78",
      "79",
      "77",
      "76"
    ],
    "correctAnswer": "77",
    "explanation": "7 × 11 = 77",
    "subject": "Mathematical Reasoning",
    "topic": "Multiplication",
    "difficulty": "hard",
    "grade": 4,
    "tags": [
      "mathematics",
      "build-time-generated",
      "timed-test-ready"
    ],
    "createdBy": "build-time-generator",
    "createdAt": "2025-08-11T14:57:08.416Z",
    "estimatedTime": 90
  },
  {
    "_id": "build_math_4_hard_23",
    "content": "What is 154 ÷ 11?",
    "type": "multiple_choice",
    "options": [
      "16",
      "15",
      "14",
      "13"
    ],
    "correctAnswer": "14",
    "explanation": "154 ÷ 11 = 14",
    "subject": "Mathematical Reasoning",
    "topic": "Division",
    "difficulty": "hard",
    "grade": 4,
    "tags": [
      "mathematics",
      "build-time-generated",
      "timed-test-ready"
    ],
    "createdBy": "build-time-generator",
    "createdAt": "2025-08-11T14:57:08.416Z",
    "estimatedTime": 90
  },
  {
    "_id": "build_math_4_hard_24",
    "content": "What is 35 + 32?",
    "type": "multiple_choice",
    "options": [
      "66",
      "69",
      "67",
      "68"
    ],
    "correctAnswer": "67",
    "explanation": "35 + 32 = 67",
    "subject": "Mathematical Reasoning",
    "topic": "Addition",
    "difficulty": "hard",
    "grade": 4,
    "tags": [
      "mathematics",
      "build-time-generated",
      "timed-test-ready"
    ],
    "createdBy": "build-time-generator",
    "createdAt": "2025-08-11T14:57:08.416Z",
    "estimatedTime": 90
  }
]