[
  {
    "_id": "reading_11_hard_1755777739629_1",
    "content": "Read this passage:\n\nThis is a hard reading passage appropriate for Grade 11 students. It contains educational content that helps develop reading comprehension skills.\n\nWhat type of passage is this?",
    "type": "multiple_choice",
    "options": [
      "A hard passage",
      "An easy passage",
      "A story",
      "A poem"
    ],
    "correctAnswer": "A hard passage",
    "subject": "reading",
    "grade": "11",
    "difficulty": "hard",
    "explanation": "The passage describes itself as a hard reading passage.",
    "_cacheBreaker": "1755777739629_0"
  },
  {
    "_id": "reading_11_hard_1755777739629_2",
    "content": "Read this passage:\n\nThis is a hard reading passage appropriate for Grade 11 students. It contains educational content that helps develop reading comprehension skills.\n\nWhat type of passage is this?",
    "type": "multiple_choice",
    "options": [
      "A hard passage",
      "An easy passage",
      "A story",
      "A poem"
    ],
    "correctAnswer": "A hard passage",
    "subject": "reading",
    "grade": "11",
    "difficulty": "hard",
    "explanation": "The passage describes itself as a hard reading passage.",
    "_cacheBreaker": "1755777739629_1"
  },
  {
    "_id": "reading_11_hard_1755777739629_3",
    "content": "Read this passage:\n\nThis is a hard reading passage appropriate for Grade 11 students. It contains educational content that helps develop reading comprehension skills.\n\nWhat type of passage is this?",
    "type": "multiple_choice",
    "options": [
      "A hard passage",
      "An easy passage",
      "A story",
      "A poem"
    ],
    "correctAnswer": "A hard passage",
    "subject": "reading",
    "grade": "11",
    "difficulty": "hard",
    "explanation": "The passage describes itself as a hard reading passage.",
    "_cacheBreaker": "1755777739629_2"
  },
  {
    "_id": "reading_11_hard_1755777739629_4",
    "content": "Read this passage:\n\nThis is a hard reading passage appropriate for Grade 11 students. It contains educational content that helps develop reading comprehension skills.\n\nWhat type of passage is this?",
    "type": "multiple_choice",
    "options": [
      "A hard passage",
      "An easy passage",
      "A story",
      "A poem"
    ],
    "correctAnswer": "A hard passage",
    "subject": "reading",
    "grade": "11",
    "difficulty": "hard",
    "explanation": "The passage describes itself as a hard reading passage.",
    "_cacheBreaker": "1755777739629_3"
  },
  {
    "_id": "reading_11_hard_1755777739629_5",
    "content": "Read this passage:\n\nThis is a hard reading passage appropriate for Grade 11 students. It contains educational content that helps develop reading comprehension skills.\n\nWhat type of passage is this?",
    "type": "multiple_choice",
    "options": [
      "A hard passage",
      "An easy passage",
      "A story",
      "A poem"
    ],
    "correctAnswer": "A hard passage",
    "subject": "reading",
    "grade": "11",
    "difficulty": "hard",
    "explanation": "The passage describes itself as a hard reading passage.",
    "_cacheBreaker": "1755777739629_4"
  },
  {
    "_id": "reading_11_hard_1755777739629_6",
    "content": "Read this passage:\n\nThis is a hard reading passage appropriate for Grade 11 students. It contains educational content that helps develop reading comprehension skills.\n\nWhat type of passage is this?",
    "type": "multiple_choice",
    "options": [
      "A hard passage",
      "An easy passage",
      "A story",
      "A poem"
    ],
    "correctAnswer": "A hard passage",
    "subject": "reading",
    "grade": "11",
    "difficulty": "hard",
    "explanation": "The passage describes itself as a hard reading passage.",
    "_cacheBreaker": "1755777739629_5"
  },
  {
    "_id": "reading_11_hard_1755777739629_7",
    "content": "Read this passage:\n\nThis is a hard reading passage appropriate for Grade 11 students. It contains educational content that helps develop reading comprehension skills.\n\nWhat type of passage is this?",
    "type": "multiple_choice",
    "options": [
      "A hard passage",
      "An easy passage",
      "A story",
      "A poem"
    ],
    "correctAnswer": "A hard passage",
    "subject": "reading",
    "grade": "11",
    "difficulty": "hard",
    "explanation": "The passage describes itself as a hard reading passage.",
    "_cacheBreaker": "1755777739629_6"
  },
  {
    "_id": "reading_11_hard_1755777739629_8",
    "content": "Read this passage:\n\nThis is a hard reading passage appropriate for Grade 11 students. It contains educational content that helps develop reading comprehension skills.\n\nWhat type of passage is this?",
    "type": "multiple_choice",
    "options": [
      "A hard passage",
      "An easy passage",
      "A story",
      "A poem"
    ],
    "correctAnswer": "A hard passage",
    "subject": "reading",
    "grade": "11",
    "difficulty": "hard",
    "explanation": "The passage describes itself as a hard reading passage.",
    "_cacheBreaker": "1755777739629_7"
  },
  {
    "_id": "reading_11_hard_1755777739629_9",
    "content": "Read this passage:\n\nThis is a hard reading passage appropriate for Grade 11 students. It contains educational content that helps develop reading comprehension skills.\n\nWhat type of passage is this?",
    "type": "multiple_choice",
    "options": [
      "A hard passage",
      "An easy passage",
      "A story",
      "A poem"
    ],
    "correctAnswer": "A hard passage",
    "subject": "reading",
    "grade": "11",
    "difficulty": "hard",
    "explanation": "The passage describes itself as a hard reading passage.",
    "_cacheBreaker": "1755777739629_8"
  },
  {
    "_id": "reading_11_hard_1755777739629_10",
    "content": "Read this passage:\n\nThis is a hard reading passage appropriate for Grade 11 students. It contains educational content that helps develop reading comprehension skills.\n\nWhat type of passage is this?",
    "type": "multiple_choice",
    "options": [
      "A hard passage",
      "An easy passage",
      "A story",
      "A poem"
    ],
    "correctAnswer": "A hard passage",
    "subject": "reading",
    "grade": "11",
    "difficulty": "hard",
    "explanation": "The passage describes itself as a hard reading passage.",
    "_cacheBreaker": "1755777739629_9"
  },
  {
    "_id": "reading_11_hard_1755777739629_11",
    "content": "Read this passage:\n\nThis is a hard reading passage appropriate for Grade 11 students. It contains educational content that helps develop reading comprehension skills.\n\nWhat type of passage is this?",
    "type": "multiple_choice",
    "options": [
      "A hard passage",
      "An easy passage",
      "A story",
      "A poem"
    ],
    "correctAnswer": "A hard passage",
    "subject": "reading",
    "grade": "11",
    "difficulty": "hard",
    "explanation": "The passage describes itself as a hard reading passage.",
    "_cacheBreaker": "1755777739629_10"
  },
  {
    "_id": "reading_11_hard_1755777739629_12",
    "content": "Read this passage:\n\nThis is a hard reading passage appropriate for Grade 11 students. It contains educational content that helps develop reading comprehension skills.\n\nWhat type of passage is this?",
    "type": "multiple_choice",
    "options": [
      "A hard passage",
      "An easy passage",
      "A story",
      "A poem"
    ],
    "correctAnswer": "A hard passage",
    "subject": "reading",
    "grade": "11",
    "difficulty": "hard",
    "explanation": "The passage describes itself as a hard reading passage.",
    "_cacheBreaker": "1755777739629_11"
  },
  {
    "_id": "reading_11_hard_1755777739629_13",
    "content": "Read this passage:\n\nThis is a hard reading passage appropriate for Grade 11 students. It contains educational content that helps develop reading comprehension skills.\n\nWhat type of passage is this?",
    "type": "multiple_choice",
    "options": [
      "A hard passage",
      "An easy passage",
      "A story",
      "A poem"
    ],
    "correctAnswer": "A hard passage",
    "subject": "reading",
    "grade": "11",
    "difficulty": "hard",
    "explanation": "The passage describes itself as a hard reading passage.",
    "_cacheBreaker": "1755777739629_12"
  },
  {
    "_id": "reading_11_hard_1755777739629_14",
    "content": "Read this passage:\n\nThis is a hard reading passage appropriate for Grade 11 students. It contains educational content that helps develop reading comprehension skills.\n\nWhat type of passage is this?",
    "type": "multiple_choice",
    "options": [
      "A hard passage",
      "An easy passage",
      "A story",
      "A poem"
    ],
    "correctAnswer": "A hard passage",
    "subject": "reading",
    "grade": "11",
    "difficulty": "hard",
    "explanation": "The passage describes itself as a hard reading passage.",
    "_cacheBreaker": "1755777739629_13"
  },
  {
    "_id": "reading_11_hard_1755777739629_15",
    "content": "Read this passage:\n\nThis is a hard reading passage appropriate for Grade 11 students. It contains educational content that helps develop reading comprehension skills.\n\nWhat type of passage is this?",
    "type": "multiple_choice",
    "options": [
      "A hard passage",
      "An easy passage",
      "A story",
      "A poem"
    ],
    "correctAnswer": "A hard passage",
    "subject": "reading",
    "grade": "11",
    "difficulty": "hard",
    "explanation": "The passage describes itself as a hard reading passage.",
    "_cacheBreaker": "1755777739629_14"
  },
  {
    "_id": "reading_11_hard_1755777739629_16",
    "content": "Read this passage:\n\nThis is a hard reading passage appropriate for Grade 11 students. It contains educational content that helps develop reading comprehension skills.\n\nWhat type of passage is this?",
    "type": "multiple_choice",
    "options": [
      "A hard passage",
      "An easy passage",
      "A story",
      "A poem"
    ],
    "correctAnswer": "A hard passage",
    "subject": "reading",
    "grade": "11",
    "difficulty": "hard",
    "explanation": "The passage describes itself as a hard reading passage.",
    "_cacheBreaker": "1755777739629_15"
  },
  {
    "_id": "reading_11_hard_1755777739629_17",
    "content": "Read this passage:\n\nThis is a hard reading passage appropriate for Grade 11 students. It contains educational content that helps develop reading comprehension skills.\n\nWhat type of passage is this?",
    "type": "multiple_choice",
    "options": [
      "A hard passage",
      "An easy passage",
      "A story",
      "A poem"
    ],
    "correctAnswer": "A hard passage",
    "subject": "reading",
    "grade": "11",
    "difficulty": "hard",
    "explanation": "The passage describes itself as a hard reading passage.",
    "_cacheBreaker": "1755777739629_16"
  },
  {
    "_id": "reading_11_hard_1755777739629_18",
    "content": "Read this passage:\n\nThis is a hard reading passage appropriate for Grade 11 students. It contains educational content that helps develop reading comprehension skills.\n\nWhat type of passage is this?",
    "type": "multiple_choice",
    "options": [
      "A hard passage",
      "An easy passage",
      "A story",
      "A poem"
    ],
    "correctAnswer": "A hard passage",
    "subject": "reading",
    "grade": "11",
    "difficulty": "hard",
    "explanation": "The passage describes itself as a hard reading passage.",
    "_cacheBreaker": "1755777739629_17"
  },
  {
    "_id": "reading_11_hard_1755777739629_19",
    "content": "Read this passage:\n\nThis is a hard reading passage appropriate for Grade 11 students. It contains educational content that helps develop reading comprehension skills.\n\nWhat type of passage is this?",
    "type": "multiple_choice",
    "options": [
      "A hard passage",
      "An easy passage",
      "A story",
      "A poem"
    ],
    "correctAnswer": "A hard passage",
    "subject": "reading",
    "grade": "11",
    "difficulty": "hard",
    "explanation": "The passage describes itself as a hard reading passage.",
    "_cacheBreaker": "1755777739629_18"
  },
  {
    "_id": "reading_11_hard_1755777739629_20",
    "content": "Read this passage:\n\nThis is a hard reading passage appropriate for Grade 11 students. It contains educational content that helps develop reading comprehension skills.\n\nWhat type of passage is this?",
    "type": "multiple_choice",
    "options": [
      "A hard passage",
      "An easy passage",
      "A story",
      "A poem"
    ],
    "correctAnswer": "A hard passage",
    "subject": "reading",
    "grade": "11",
    "difficulty": "hard",
    "explanation": "The passage describes itself as a hard reading passage.",
    "_cacheBreaker": "1755777739629_19"
  }
]