[
  {
    "_id": "math_12_hard_001",
    "content": "Solve: 12x - 24 = 11x + 36",
    "type": "multiple_choice",
    "options": [
      "x = 60",
      "x = 48",
      "x = 72",
      "x = 36"
    ],
    "correctAnswer": "x = 60",
    "subject": "math",
    "grade": "12",
    "difficulty": "hard",
    "explanation": "12x - 11x = 36 + 24, so x = 60",
    "_cacheBreaker": "1756033578449_1"
  },
  {
    "_id": "math_12_hard_002",
    "content": "If f(x) = 12x² + 24x, what is f(12)?",
    "type": "multiple_choice",
    "options": [
      "2016",
      "168",
      "36",
      "144"
    ],
    "correctAnswer": "2016",
    "subject": "math",
    "grade": "12",
    "difficulty": "hard",
    "explanation": "f(12) = 12(12)² + 24(12) = 1728 + 288 = 2016",
    "_cacheBreaker": "1756033578449_2"
  },
  {
    "_id": "math_12_hard_003",
    "content": "What is the vertex of the parabola y = x² - 24x + 12?",
    "type": "multiple_choice",
    "options": [
      "(12, -12)",
      "(12, 0)",
      "(0, 12)",
      "(12, 12)"
    ],
    "correctAnswer": "(12, -12)",
    "subject": "math",
    "grade": "12",
    "difficulty": "hard",
    "explanation": "Vertex x-coordinate = -b/2a = 24/2 = 12. y = 12² - 24(12) + 12 = -12",
    "_cacheBreaker": "1756033578449_3"
  },
  {
    "_id": "math_12_hard_004",
    "content": "Factor completely: x² - 144",
    "type": "multiple_choice",
    "options": [
      "(x - 12)(x + 12)",
      "(x - 12)²",
      "x(x - 12)",
      "Cannot be factored"
    ],
    "correctAnswer": "(x - 12)(x + 12)",
    "subject": "math",
    "grade": "12",
    "difficulty": "hard",
    "explanation": "x² - 144 is a difference of squares: (x - 12)(x + 12)",
    "_cacheBreaker": "1756033578449_4"
  },
  {
    "_id": "math_12_hard_005",
    "content": "What is the range of f(x) = -x² + 24?",
    "type": "multiple_choice",
    "options": [
      "All real numbers",
      "y ≤ 24",
      "y ≥ 24",
      "y > 0"
    ],
    "correctAnswer": "y ≤ 24",
    "subject": "math",
    "grade": "12",
    "difficulty": "hard",
    "explanation": "Since the parabola opens downward, the maximum value is 24",
    "_cacheBreaker": "1756033578449_5"
  },
  {
    "_id": "math_12_hard_006",
    "content": "Solve: 12x - 24 = 11x + 36",
    "type": "multiple_choice",
    "options": [
      "x = 60",
      "x = 48",
      "x = 72",
      "x = 36"
    ],
    "correctAnswer": "x = 60",
    "subject": "math",
    "grade": "12",
    "difficulty": "hard",
    "explanation": "12x - 11x = 36 + 24, so x = 60",
    "_cacheBreaker": "1756033578449_6"
  },
  {
    "_id": "math_12_hard_007",
    "content": "If f(x) = 12x² + 24x, what is f(12)?",
    "type": "multiple_choice",
    "options": [
      "2016",
      "168",
      "36",
      "144"
    ],
    "correctAnswer": "2016",
    "subject": "math",
    "grade": "12",
    "difficulty": "hard",
    "explanation": "f(12) = 12(12)² + 24(12) = 1728 + 288 = 2016",
    "_cacheBreaker": "1756033578449_7"
  },
  {
    "_id": "math_12_hard_008",
    "content": "What is the vertex of the parabola y = x² - 24x + 12?",
    "type": "multiple_choice",
    "options": [
      "(12, -12)",
      "(12, 0)",
      "(0, 12)",
      "(12, 12)"
    ],
    "correctAnswer": "(12, -12)",
    "subject": "math",
    "grade": "12",
    "difficulty": "hard",
    "explanation": "Vertex x-coordinate = -b/2a = 24/2 = 12. y = 12² - 24(12) + 12 = -12",
    "_cacheBreaker": "1756033578449_8"
  },
  {
    "_id": "math_12_hard_009",
    "content": "Factor completely: x² - 144",
    "type": "multiple_choice",
    "options": [
      "(x - 12)(x + 12)",
      "(x - 12)²",
      "x(x - 12)",
      "Cannot be factored"
    ],
    "correctAnswer": "(x - 12)(x + 12)",
    "subject": "math",
    "grade": "12",
    "difficulty": "hard",
    "explanation": "x² - 144 is a difference of squares: (x - 12)(x + 12)",
    "_cacheBreaker": "1756033578449_9"
  },
  {
    "_id": "math_12_hard_010",
    "content": "What is the range of f(x) = -x² + 24?",
    "type": "multiple_choice",
    "options": [
      "All real numbers",
      "y ≤ 24",
      "y ≥ 24",
      "y > 0"
    ],
    "correctAnswer": "y ≤ 24",
    "subject": "math",
    "grade": "12",
    "difficulty": "hard",
    "explanation": "Since the parabola opens downward, the maximum value is 24",
    "_cacheBreaker": "1756033578449_10"
  },
  {
    "_id": "math_12_hard_011",
    "content": "Solve: 12x - 24 = 11x + 36",
    "type": "multiple_choice",
    "options": [
      "x = 60",
      "x = 48",
      "x = 72",
      "x = 36"
    ],
    "correctAnswer": "x = 60",
    "subject": "math",
    "grade": "12",
    "difficulty": "hard",
    "explanation": "12x - 11x = 36 + 24, so x = 60",
    "_cacheBreaker": "1756033578449_11"
  },
  {
    "_id": "math_12_hard_012",
    "content": "If f(x) = 12x² + 24x, what is f(12)?",
    "type": "multiple_choice",
    "options": [
      "2016",
      "168",
      "36",
      "144"
    ],
    "correctAnswer": "2016",
    "subject": "math",
    "grade": "12",
    "difficulty": "hard",
    "explanation": "f(12) = 12(12)² + 24(12) = 1728 + 288 = 2016",
    "_cacheBreaker": "1756033578449_12"
  },
  {
    "_id": "math_12_hard_013",
    "content": "What is the vertex of the parabola y = x² - 24x + 12?",
    "type": "multiple_choice",
    "options": [
      "(12, -12)",
      "(12, 0)",
      "(0, 12)",
      "(12, 12)"
    ],
    "correctAnswer": "(12, -12)",
    "subject": "math",
    "grade": "12",
    "difficulty": "hard",
    "explanation": "Vertex x-coordinate = -b/2a = 24/2 = 12. y = 12² - 24(12) + 12 = -12",
    "_cacheBreaker": "1756033578449_13"
  },
  {
    "_id": "math_12_hard_014",
    "content": "Factor completely: x² - 144",
    "type": "multiple_choice",
    "options": [
      "(x - 12)(x + 12)",
      "(x - 12)²",
      "x(x - 12)",
      "Cannot be factored"
    ],
    "correctAnswer": "(x - 12)(x + 12)",
    "subject": "math",
    "grade": "12",
    "difficulty": "hard",
    "explanation": "x² - 144 is a difference of squares: (x - 12)(x + 12)",
    "_cacheBreaker": "1756033578449_14"
  },
  {
    "_id": "math_12_hard_015",
    "content": "What is the range of f(x) = -x² + 24?",
    "type": "multiple_choice",
    "options": [
      "All real numbers",
      "y ≤ 24",
      "y ≥ 24",
      "y > 0"
    ],
    "correctAnswer": "y ≤ 24",
    "subject": "math",
    "grade": "12",
    "difficulty": "hard",
    "explanation": "Since the parabola opens downward, the maximum value is 24",
    "_cacheBreaker": "1756033578449_15"
  },
  {
    "_id": "math_12_hard_016",
    "content": "Solve: 12x - 24 = 11x + 36",
    "type": "multiple_choice",
    "options": [
      "x = 60",
      "x = 48",
      "x = 72",
      "x = 36"
    ],
    "correctAnswer": "x = 60",
    "subject": "math",
    "grade": "12",
    "difficulty": "hard",
    "explanation": "12x - 11x = 36 + 24, so x = 60",
    "_cacheBreaker": "1756033578449_16"
  },
  {
    "_id": "math_12_hard_017",
    "content": "If f(x) = 12x² + 24x, what is f(12)?",
    "type": "multiple_choice",
    "options": [
      "2016",
      "168",
      "36",
      "144"
    ],
    "correctAnswer": "2016",
    "subject": "math",
    "grade": "12",
    "difficulty": "hard",
    "explanation": "f(12) = 12(12)² + 24(12) = 1728 + 288 = 2016",
    "_cacheBreaker": "1756033578449_17"
  },
  {
    "_id": "math_12_hard_018",
    "content": "What is the vertex of the parabola y = x² - 24x + 12?",
    "type": "multiple_choice",
    "options": [
      "(12, -12)",
      "(12, 0)",
      "(0, 12)",
      "(12, 12)"
    ],
    "correctAnswer": "(12, -12)",
    "subject": "math",
    "grade": "12",
    "difficulty": "hard",
    "explanation": "Vertex x-coordinate = -b/2a = 24/2 = 12. y = 12² - 24(12) + 12 = -12",
    "_cacheBreaker": "1756033578449_18"
  },
  {
    "_id": "math_12_hard_019",
    "content": "Factor completely: x² - 144",
    "type": "multiple_choice",
    "options": [
      "(x - 12)(x + 12)",
      "(x - 12)²",
      "x(x - 12)",
      "Cannot be factored"
    ],
    "correctAnswer": "(x - 12)(x + 12)",
    "subject": "math",
    "grade": "12",
    "difficulty": "hard",
    "explanation": "x² - 144 is a difference of squares: (x - 12)(x + 12)",
    "_cacheBreaker": "1756033578449_19"
  },
  {
    "_id": "math_12_hard_020",
    "content": "What is the range of f(x) = -x² + 24?",
    "type": "multiple_choice",
    "options": [
      "All real numbers",
      "y ≤ 24",
      "y ≥ 24",
      "y > 0"
    ],
    "correctAnswer": "y ≤ 24",
    "subject": "math",
    "grade": "12",
    "difficulty": "hard",
    "explanation": "Since the parabola opens downward, the maximum value is 24",
    "_cacheBreaker": "1756033578449_20"
  },
  {
    "_id": "math_12_hard_021",
    "content": "Solve: 12x - 24 = 11x + 36",
    "type": "multiple_choice",
    "options": [
      "x = 60",
      "x = 48",
      "x = 72",
      "x = 36"
    ],
    "correctAnswer": "x = 60",
    "subject": "math",
    "grade": "12",
    "difficulty": "hard",
    "explanation": "12x - 11x = 36 + 24, so x = 60",
    "_cacheBreaker": "1756033578449_21"
  },
  {
    "_id": "math_12_hard_022",
    "content": "If f(x) = 12x² + 24x, what is f(12)?",
    "type": "multiple_choice",
    "options": [
      "2016",
      "168",
      "36",
      "144"
    ],
    "correctAnswer": "2016",
    "subject": "math",
    "grade": "12",
    "difficulty": "hard",
    "explanation": "f(12) = 12(12)² + 24(12) = 1728 + 288 = 2016",
    "_cacheBreaker": "1756033578449_22"
  },
  {
    "_id": "math_12_hard_023",
    "content": "What is the vertex of the parabola y = x² - 24x + 12?",
    "type": "multiple_choice",
    "options": [
      "(12, -12)",
      "(12, 0)",
      "(0, 12)",
      "(12, 12)"
    ],
    "correctAnswer": "(12, -12)",
    "subject": "math",
    "grade": "12",
    "difficulty": "hard",
    "explanation": "Vertex x-coordinate = -b/2a = 24/2 = 12. y = 12² - 24(12) + 12 = -12",
    "_cacheBreaker": "1756033578449_23"
  },
  {
    "_id": "math_12_hard_024",
    "content": "Factor completely: x² - 144",
    "type": "multiple_choice",
    "options": [
      "(x - 12)(x + 12)",
      "(x - 12)²",
      "x(x - 12)",
      "Cannot be factored"
    ],
    "correctAnswer": "(x - 12)(x + 12)",
    "subject": "math",
    "grade": "12",
    "difficulty": "hard",
    "explanation": "x² - 144 is a difference of squares: (x - 12)(x + 12)",
    "_cacheBreaker": "1756033578449_24"
  },
  {
    "_id": "math_12_hard_025",
    "content": "What is the range of f(x) = -x² + 24?",
    "type": "multiple_choice",
    "options": [
      "All real numbers",
      "y ≤ 24",
      "y ≥ 24",
      "y > 0"
    ],
    "correctAnswer": "y ≤ 24",
    "subject": "math",
    "grade": "12",
    "difficulty": "hard",
    "explanation": "Since the parabola opens downward, the maximum value is 24",
    "_cacheBreaker": "1756033578449_25"
  },
  {
    "_id": "math_12_hard_026",
    "content": "Solve: 12x - 24 = 11x + 36",
    "type": "multiple_choice",
    "options": [
      "x = 60",
      "x = 48",
      "x = 72",
      "x = 36"
    ],
    "correctAnswer": "x = 60",
    "subject": "math",
    "grade": "12",
    "difficulty": "hard",
    "explanation": "12x - 11x = 36 + 24, so x = 60",
    "_cacheBreaker": "1756033578449_26"
  },
  {
    "_id": "math_12_hard_027",
    "content": "If f(x) = 12x² + 24x, what is f(12)?",
    "type": "multiple_choice",
    "options": [
      "2016",
      "168",
      "36",
      "144"
    ],
    "correctAnswer": "2016",
    "subject": "math",
    "grade": "12",
    "difficulty": "hard",
    "explanation": "f(12) = 12(12)² + 24(12) = 1728 + 288 = 2016",
    "_cacheBreaker": "1756033578449_27"
  },
  {
    "_id": "math_12_hard_028",
    "content": "What is the vertex of the parabola y = x² - 24x + 12?",
    "type": "multiple_choice",
    "options": [
      "(12, -12)",
      "(12, 0)",
      "(0, 12)",
      "(12, 12)"
    ],
    "correctAnswer": "(12, -12)",
    "subject": "math",
    "grade": "12",
    "difficulty": "hard",
    "explanation": "Vertex x-coordinate = -b/2a = 24/2 = 12. y = 12² - 24(12) + 12 = -12",
    "_cacheBreaker": "1756033578449_28"
  },
  {
    "_id": "math_12_hard_029",
    "content": "Factor completely: x² - 144",
    "type": "multiple_choice",
    "options": [
      "(x - 12)(x + 12)",
      "(x - 12)²",
      "x(x - 12)",
      "Cannot be factored"
    ],
    "correctAnswer": "(x - 12)(x + 12)",
    "subject": "math",
    "grade": "12",
    "difficulty": "hard",
    "explanation": "x² - 144 is a difference of squares: (x - 12)(x + 12)",
    "_cacheBreaker": "1756033578449_29"
  },
  {
    "_id": "math_12_hard_030",
    "content": "What is the range of f(x) = -x² + 24?",
    "type": "multiple_choice",
    "options": [
      "All real numbers",
      "y ≤ 24",
      "y ≥ 24",
      "y > 0"
    ],
    "correctAnswer": "y ≤ 24",
    "subject": "math",
    "grade": "12",
    "difficulty": "hard",
    "explanation": "Since the parabola opens downward, the maximum value is 24",
    "_cacheBreaker": "1756033578449_30"
  },
  {
    "_id": "math_12_hard_031",
    "content": "Solve: 12x - 24 = 11x + 36",
    "type": "multiple_choice",
    "options": [
      "x = 60",
      "x = 48",
      "x = 72",
      "x = 36"
    ],
    "correctAnswer": "x = 60",
    "subject": "math",
    "grade": "12",
    "difficulty": "hard",
    "explanation": "12x - 11x = 36 + 24, so x = 60",
    "_cacheBreaker": "1756033578449_31"
  },
  {
    "_id": "math_12_hard_032",
    "content": "If f(x) = 12x² + 24x, what is f(12)?",
    "type": "multiple_choice",
    "options": [
      "2016",
      "168",
      "36",
      "144"
    ],
    "correctAnswer": "2016",
    "subject": "math",
    "grade": "12",
    "difficulty": "hard",
    "explanation": "f(12) = 12(12)² + 24(12) = 1728 + 288 = 2016",
    "_cacheBreaker": "1756033578449_32"
  },
  {
    "_id": "math_12_hard_033",
    "content": "What is the vertex of the parabola y = x² - 24x + 12?",
    "type": "multiple_choice",
    "options": [
      "(12, -12)",
      "(12, 0)",
      "(0, 12)",
      "(12, 12)"
    ],
    "correctAnswer": "(12, -12)",
    "subject": "math",
    "grade": "12",
    "difficulty": "hard",
    "explanation": "Vertex x-coordinate = -b/2a = 24/2 = 12. y = 12² - 24(12) + 12 = -12",
    "_cacheBreaker": "1756033578449_33"
  },
  {
    "_id": "math_12_hard_034",
    "content": "Factor completely: x² - 144",
    "type": "multiple_choice",
    "options": [
      "(x - 12)(x + 12)",
      "(x - 12)²",
      "x(x - 12)",
      "Cannot be factored"
    ],
    "correctAnswer": "(x - 12)(x + 12)",
    "subject": "math",
    "grade": "12",
    "difficulty": "hard",
    "explanation": "x² - 144 is a difference of squares: (x - 12)(x + 12)",
    "_cacheBreaker": "1756033578449_34"
  },
  {
    "_id": "math_12_hard_035",
    "content": "What is the range of f(x) = -x² + 24?",
    "type": "multiple_choice",
    "options": [
      "All real numbers",
      "y ≤ 24",
      "y ≥ 24",
      "y > 0"
    ],
    "correctAnswer": "y ≤ 24",
    "subject": "math",
    "grade": "12",
    "difficulty": "hard",
    "explanation": "Since the parabola opens downward, the maximum value is 24",
    "_cacheBreaker": "1756033578449_35"
  },
  {
    "_id": "math_12_hard_036",
    "content": "Solve: 12x - 24 = 11x + 36",
    "type": "multiple_choice",
    "options": [
      "x = 60",
      "x = 48",
      "x = 72",
      "x = 36"
    ],
    "correctAnswer": "x = 60",
    "subject": "math",
    "grade": "12",
    "difficulty": "hard",
    "explanation": "12x - 11x = 36 + 24, so x = 60",
    "_cacheBreaker": "1756033578449_36"
  },
  {
    "_id": "math_12_hard_037",
    "content": "If f(x) = 12x² + 24x, what is f(12)?",
    "type": "multiple_choice",
    "options": [
      "2016",
      "168",
      "36",
      "144"
    ],
    "correctAnswer": "2016",
    "subject": "math",
    "grade": "12",
    "difficulty": "hard",
    "explanation": "f(12) = 12(12)² + 24(12) = 1728 + 288 = 2016",
    "_cacheBreaker": "1756033578449_37"
  },
  {
    "_id": "math_12_hard_038",
    "content": "What is the vertex of the parabola y = x² - 24x + 12?",
    "type": "multiple_choice",
    "options": [
      "(12, -12)",
      "(12, 0)",
      "(0, 12)",
      "(12, 12)"
    ],
    "correctAnswer": "(12, -12)",
    "subject": "math",
    "grade": "12",
    "difficulty": "hard",
    "explanation": "Vertex x-coordinate = -b/2a = 24/2 = 12. y = 12² - 24(12) + 12 = -12",
    "_cacheBreaker": "1756033578449_38"
  },
  {
    "_id": "math_12_hard_039",
    "content": "Factor completely: x² - 144",
    "type": "multiple_choice",
    "options": [
      "(x - 12)(x + 12)",
      "(x - 12)²",
      "x(x - 12)",
      "Cannot be factored"
    ],
    "correctAnswer": "(x - 12)(x + 12)",
    "subject": "math",
    "grade": "12",
    "difficulty": "hard",
    "explanation": "x² - 144 is a difference of squares: (x - 12)(x + 12)",
    "_cacheBreaker": "1756033578449_39"
  },
  {
    "_id": "math_12_hard_040",
    "content": "What is the range of f(x) = -x² + 24?",
    "type": "multiple_choice",
    "options": [
      "All real numbers",
      "y ≤ 24",
      "y ≥ 24",
      "y > 0"
    ],
    "correctAnswer": "y ≤ 24",
    "subject": "math",
    "grade": "12",
    "difficulty": "hard",
    "explanation": "Since the parabola opens downward, the maximum value is 24",
    "_cacheBreaker": "1756033578449_40"
  },
  {
    "_id": "math_12_hard_041",
    "content": "Solve: 12x - 24 = 11x + 36",
    "type": "multiple_choice",
    "options": [
      "x = 60",
      "x = 48",
      "x = 72",
      "x = 36"
    ],
    "correctAnswer": "x = 60",
    "subject": "math",
    "grade": "12",
    "difficulty": "hard",
    "explanation": "12x - 11x = 36 + 24, so x = 60",
    "_cacheBreaker": "1756033578449_41"
  },
  {
    "_id": "math_12_hard_042",
    "content": "If f(x) = 12x² + 24x, what is f(12)?",
    "type": "multiple_choice",
    "options": [
      "2016",
      "168",
      "36",
      "144"
    ],
    "correctAnswer": "2016",
    "subject": "math",
    "grade": "12",
    "difficulty": "hard",
    "explanation": "f(12) = 12(12)² + 24(12) = 1728 + 288 = 2016",
    "_cacheBreaker": "1756033578449_42"
  },
  {
    "_id": "math_12_hard_043",
    "content": "What is the vertex of the parabola y = x² - 24x + 12?",
    "type": "multiple_choice",
    "options": [
      "(12, -12)",
      "(12, 0)",
      "(0, 12)",
      "(12, 12)"
    ],
    "correctAnswer": "(12, -12)",
    "subject": "math",
    "grade": "12",
    "difficulty": "hard",
    "explanation": "Vertex x-coordinate = -b/2a = 24/2 = 12. y = 12² - 24(12) + 12 = -12",
    "_cacheBreaker": "1756033578449_43"
  },
  {
    "_id": "math_12_hard_044",
    "content": "Factor completely: x² - 144",
    "type": "multiple_choice",
    "options": [
      "(x - 12)(x + 12)",
      "(x - 12)²",
      "x(x - 12)",
      "Cannot be factored"
    ],
    "correctAnswer": "(x - 12)(x + 12)",
    "subject": "math",
    "grade": "12",
    "difficulty": "hard",
    "explanation": "x² - 144 is a difference of squares: (x - 12)(x + 12)",
    "_cacheBreaker": "1756033578449_44"
  },
  {
    "_id": "math_12_hard_045",
    "content": "What is the range of f(x) = -x² + 24?",
    "type": "multiple_choice",
    "options": [
      "All real numbers",
      "y ≤ 24",
      "y ≥ 24",
      "y > 0"
    ],
    "correctAnswer": "y ≤ 24",
    "subject": "math",
    "grade": "12",
    "difficulty": "hard",
    "explanation": "Since the parabola opens downward, the maximum value is 24",
    "_cacheBreaker": "1756033578449_45"
  },
  {
    "_id": "math_12_hard_046",
    "content": "Solve: 12x - 24 = 11x + 36",
    "type": "multiple_choice",
    "options": [
      "x = 60",
      "x = 48",
      "x = 72",
      "x = 36"
    ],
    "correctAnswer": "x = 60",
    "subject": "math",
    "grade": "12",
    "difficulty": "hard",
    "explanation": "12x - 11x = 36 + 24, so x = 60",
    "_cacheBreaker": "1756033578449_46"
  },
  {
    "_id": "math_12_hard_047",
    "content": "If f(x) = 12x² + 24x, what is f(12)?",
    "type": "multiple_choice",
    "options": [
      "2016",
      "168",
      "36",
      "144"
    ],
    "correctAnswer": "2016",
    "subject": "math",
    "grade": "12",
    "difficulty": "hard",
    "explanation": "f(12) = 12(12)² + 24(12) = 1728 + 288 = 2016",
    "_cacheBreaker": "1756033578449_47"
  },
  {
    "_id": "math_12_hard_048",
    "content": "What is the vertex of the parabola y = x² - 24x + 12?",
    "type": "multiple_choice",
    "options": [
      "(12, -12)",
      "(12, 0)",
      "(0, 12)",
      "(12, 12)"
    ],
    "correctAnswer": "(12, -12)",
    "subject": "math",
    "grade": "12",
    "difficulty": "hard",
    "explanation": "Vertex x-coordinate = -b/2a = 24/2 = 12. y = 12² - 24(12) + 12 = -12",
    "_cacheBreaker": "1756033578449_48"
  },
  {
    "_id": "math_12_hard_049",
    "content": "Factor completely: x² - 144",
    "type": "multiple_choice",
    "options": [
      "(x - 12)(x + 12)",
      "(x - 12)²",
      "x(x - 12)",
      "Cannot be factored"
    ],
    "correctAnswer": "(x - 12)(x + 12)",
    "subject": "math",
    "grade": "12",
    "difficulty": "hard",
    "explanation": "x² - 144 is a difference of squares: (x - 12)(x + 12)",
    "_cacheBreaker": "1756033578449_49"
  },
  {
    "_id": "math_12_hard_050",
    "content": "What is the range of f(x) = -x² + 24?",
    "type": "multiple_choice",
    "options": [
      "All real numbers",
      "y ≤ 24",
      "y ≥ 24",
      "y > 0"
    ],
    "correctAnswer": "y ≤ 24",
    "subject": "math",
    "grade": "12",
    "difficulty": "hard",
    "explanation": "Since the parabola opens downward, the maximum value is 24",
    "_cacheBreaker": "1756033578449_50"
  }
]